README.rst
setup.py
cellardoor/__init__.py
cellardoor/authorization.py
cellardoor/errors.py
cellardoor/events.py
cellardoor/version.py
cellardoor.egg-info/PKG-INFO
cellardoor.egg-info/SOURCES.txt
cellardoor.egg-info/dependency_links.txt
cellardoor.egg-info/requires.txt
cellardoor.egg-info/top_level.txt
cellardoor/api/__init__.py
cellardoor/api/interface.py
cellardoor/api/methods.py
cellardoor/authentication/__init__.py
cellardoor/authentication/basic.py
cellardoor/authentication/token.py
cellardoor/model/__init__.py
cellardoor/model/dateparsers.py
cellardoor/model/fields.py
cellardoor/model/mixins.py
cellardoor/model/model.py
cellardoor/serializers/__init__.py
cellardoor/serializers/json_serializer.py
cellardoor/serializers/msgpack_serializer.py
cellardoor/spec/__init__.py
cellardoor/spec/jsonschema.py
cellardoor/storage/__init__.py
cellardoor/storage/mongodb.py
cellardoor/views/__init__.py
cellardoor/views/minimal.py
cellardoor/wsgi/__init__.py
cellardoor/wsgi/falcon_integration.py
cellardoor/wsgi/flask_integration.py