Metadata-Version: 1.1
Name: cellardoor
Version: 0.3.4
Summary: Create CRUD APIs how you've always wanted.
Home-page: http://github.com/cooper-software/cellardoor
Author: Elisha Fitch-Cook
Author-email: elisha@cooper.com
License: MIT
Keywords: wsgi web api framework rest http cloud
Platform: UNKNOWN
Classifier: Development Status :: 1 - Planning
Classifier: Environment :: Web Environment
Classifier: Natural Language :: English
Classifier: Intended Audience :: Developers
Classifier: License :: OSI Approved :: MIT License
Classifier: Operating System :: MacOS :: MacOS X
Classifier: Operating System :: Microsoft :: Windows
Classifier: Operating System :: POSIX
Classifier: Topic :: Internet :: WWW/HTTP :: WSGI
Classifier: Topic :: Software Development :: Libraries :: Application Frameworks
Classifier: Programming Language :: Python
Classifier: Programming Language :: Python :: 2.6
Classifier: Programming Language :: Python :: 2.7
